<?xml version="1.0" encoding="UTF-8"?><artifacts>
    <artifact name="TimeoutAPI" groupId="wso2.sampleExceptionHandlingTemplate.api" version="1.0.0" type="synapse/api" serverRole="EnterpriseServiceBus">
        <file>src/main/synapse-config/api/TimeoutAPI.xml</file>
    </artifact>
    <artifact name="TimeoutAPI_swagger" groupId="wso2.sampleExceptionHandlingTemplate.metadata" version="1.0.0" type="synapse/metadata" serverRole="EnterpriseServiceBus">
        <file>src/main/resources/metadata/TimeoutAPI_swagger.yaml</file>
    </artifact>
    <artifact name="TimeoutAPI_metadata" groupId="wso2.sampleExceptionHandlingTemplate.metadata" version="1.0.0" type="synapse/metadata" serverRole="EnterpriseServiceBus">
        <file>src/main/resources/metadata/TimeoutAPI_metadata.yaml</file>
    </artifact>
    <artifact name="TimeoutFailureSeq" groupId="wso2.sampleExceptionHandlingTemplate.sequence" version="1.0.0" type="synapse/sequence" serverRole="EnterpriseServiceBus">
        <file>src/main/synapse-config/sequences/TimeoutFailureSeq.xml</file>
    </artifact>
    <artifact name="DelayHttpEP" groupId="wso2.sampleExceptionHandlingTemplate.endpoint" version="1.0.0" type="synapse/endpoint" serverRole="EnterpriseServiceBus">
        <file>src/main/synapse-config/endpoints/DelayHttpEP.xml</file>
    </artifact>
</artifacts>
